db/__init__.py
db/column.py
db/db.py
db/query_templates.py
db/s3.py
db/table.py
db/utils.py
db/data/chinook.sqlite
db/queries/__init__.py
db/queries/bigquery.py
db/queries/mssql.py
db/queries/mysql.py
db/queries/postgres.py
db/queries/redshift.py
db/queries/sqlite.py
db/tests/__init__.py
db/tests/tests-mysql.py
db/tests/tests-postgres.py
db/tests/tests.py
rafa_db-0.6.0.dist-info/DESCRIPTION.rst
rafa_db-0.6.0.dist-info/METADATA
rafa_db-0.6.0.dist-info/RECORD
rafa_db-0.6.0.dist-info/WHEEL
rafa_db-0.6.0.dist-info/metadata.json
rafa_db-0.6.0.dist-info/top_level.txt
