Metadata-Version: 2.0
Name: rafa-db
Version: 0.6.0
Summary: a db package that doesn't suck
Home-page: https://github.com/mjirv/db.py
Author: Michael Irvine
Author-email: michael.j.irvine@gmail.com
License: BSD
Platform: UNKNOWN
Classifier: Development Status :: 4 - Beta
Classifier: License :: OSI Approved :: BSD License
Classifier: Programming Language :: Python :: 2
Classifier: Programming Language :: Python :: 2.6
Classifier: Programming Language :: Python :: 2.7
Classifier: Programming Language :: Python :: 3
Classifier: Programming Language :: Python :: 3.2
Classifier: Programming Language :: Python :: 3.3
Classifier: Programming Language :: Python :: 3.4
License-File: LICENSE
Requires-Dist: prettytable (==0.7.2)
Requires-Dist: pandas
Requires-Dist: pybars3
